Metadata-Version: 2.4
Name: httpinsert
Version: 2.0.2
Summary: HTTPInsert - Inserting payloads into all sections of HTTP requests
Author: William Kristoffersen
Author-email: william.kristof@gmail.com
License: MIT
Keywords: python,httpinsert
License-File: LICENSE
Requires-Dist: multipart
Requires-Dist: requests
Requires-Dist: lxml
Dynamic: author
Dynamic: author-email
Dynamic: description
Dynamic: description-content-type
Dynamic: keywords
Dynamic: license
Dynamic: license-file
Dynamic: requires-dist
Dynamic: summary
